{
  "name": "Zwift TTT Race Simulator",
  "image": "mcr.microsoft.com/devcontainers/dotnet:1-10.0-bookworm",
  
  "features": {
    "ghcr.io/devcontainers/features/git:1": {},
    "ghcr.io/devcontainers/features/github-cli:1": {}
  },

  "customizations": {
    "vscode": {
      "extensions": [
        "ms-dotnettools.csharp",
        "ms-dotnettools.csdevkit",
        "ms-dotnettools.vscode-dotnet-runtime"
      ],
      "settings": {
        "dotnet.defaultSolution": "ZwiftTTTSim.sln"
      }
    }
  },

  "postCreateCommand": "dotnet restore",

  "remoteUser": "vscode"
}
